anyblok_marshmallow/__init__.py
anyblok_marshmallow/conftest.py
anyblok_marshmallow/exceptions.py
anyblok_marshmallow/fields.py
anyblok_marshmallow/release.py
anyblok_marshmallow/schema.py
anyblok_marshmallow/tests/__init__.py
anyblok_marshmallow/tests/conftest.py
anyblok_marshmallow/tests/test_complexe_model.py
anyblok_marshmallow/tests/test_decorator.py
anyblok_marshmallow/tests/test_fields.py
anyblok_marshmallow/tests/test_model.py
anyblok_marshmallow/tests/test_only_primary_key.py
anyblok_marshmallow/tests/test_polymorphism.py
anyblok_marshmallow/tests/test_post_load_return_instance.py
anyblok_marshmallow/tests/test_registry.py
anyblok_marshmallow/tests/test_relationship.py
anyblok_marshmallow/tests/test_required.py
anyblok_marshmallow/tests/test_simple_model.py
anyblok_marshmallow-2.3.0.dist-info/LICENSE.rst
anyblok_marshmallow-2.3.0.dist-info/METADATA
anyblok_marshmallow-2.3.0.dist-info/WHEEL
anyblok_marshmallow-2.3.0.dist-info/top_level.txt
anyblok_marshmallow-2.3.0.dist-info/RECORD
