Metadata-Version: 2.1
Name: anyblok-marshmallow
Version: 2.3.0
Summary: Add validator, serializer and deserializer to AnyBlok
Home-page: https://anyblok-marshmallow.readthedocs.io/en/2.3.0
Author: Jean-Sébastien SUZANNE
Author-email: jssuzanne@anybox.fr
License: UNKNOWN
Keywords: anyblok_marshmallow
Platform: UNKNOWN
Classifier: Development Status :: 5 - Production/Stable
Classifier: Intended Audience :: Developers
Classifier: Natural Language :: English
Classifier: Programming Language :: Python :: 3 :: Only
Classifier: Programming Language :: Python :: 3.6
Classifier: Programming Language :: Python :: 3.7
Classifier: Programming Language :: Python :: 3.8
Classifier: Topic :: Software Development :: Libraries :: Python Modules
Classifier: License :: OSI Approved :: Mozilla Public License 2.0 (MPL 2.0)
Requires-Dist: anyblok
Requires-Dist: marshmallow (>=3.2.1)
Requires-Dist: marshmallow-sqlalchemy (>=0.19.0)
